Metadata-Version: 2.1
Name: thonny-black-formatter
Version: 0.0.4
Summary: A plugin to format your python code with Black in Thonny IDE. (For Thonny release >= 4.x)
Author-email: Ettore Galli <ettore.galli@gmail.com>
License: MIT License        
Project-URL: Homepage, https://github.com/ettore-galli/thonny-black-formatter
Keywords: thonny,black,formatter
Classifier: License :: OSI Approved :: MIT License
Classifier: Programming Language :: Python
Classifier: Programming Language :: Python :: 3
Requires-Python: >=3.9
License-File: LICENSE
Requires-Dist: black
Provides-Extra: dev
Requires-Dist: pip-tools ; extra == 'dev'
Requires-Dist: thonny ; extra == 'dev'
Requires-Dist: bumpver ; extra == 'dev'
